pydockerhub/__init__.py
pydockerhub/api_calls/__init__.py
pydockerhub/api_calls/caller.py
pydockerhub/api_calls/errors.py
pydockerhub/api_calls/request.py
pydockerhub/api_calls/response.py
pydockerhub/api_calls/types.py
pydockerhub/client.py
pydockerhub/error.py
pydockerhub/exception.py
pydockerhub/hub/__init__.py
pydockerhub/hub/actions.py
pydockerhub/hub/errors.py
pydockerhub/hub/models.py
pydockerhub/hub/types.py
pydockerhub/raw_http/__init__.py
pydockerhub/raw_http/client.py
pydockerhub/raw_http/errors.py
pydockerhub/raw_http/types.py
pydockerhub-1.2.1.dist-info/LICENSE
pydockerhub-1.2.1.dist-info/METADATA
pydockerhub-1.2.1.dist-info/WHEEL
pydockerhub-1.2.1.dist-info/RECORD
