Metadata-Version: 2.1
Name: pydockerhub
Version: 1.2.1
Summary: Extended Docker Hub API Client
Home-page: https://github.com/9orky/py_dockerhub
License: Apache-2.0
Author: Tomasz Szpak
Author-email: tomszp@gmail.com
Requires-Python: >=3.12,<4.0
Classifier: License :: OSI Approved :: Apache Software License
Classifier: Programming Language :: Python :: 3
Classifier: Programming Language :: Python :: 3.12
Requires-Dist: httpx (>=0.27.0,<0.28.0)
Requires-Dist: pydantic (>=2.7.1,<3.0.0)
Requires-Dist: setuptools (>=69.2.0,<70.0.0)
Project-URL: Repository, https://github.com/9orky/py_dockerhub
